gp32_transfer/__init__.py
gp32_transfer/main.py
gp32_transfer/utils/__init__.py
gp32_transfer/utils/const.py
gp32_transfer/utils/furuno_read.py
gp32_transfer/utils/furuno_write.py
gp32_transfer/utils/serial_util.py
gp32_transfer-0.2.2.dist-info/entry_points.txt
gp32_transfer-0.2.2.dist-info/WHEEL
gp32_transfer-0.2.2.dist-info/METADATA
gp32_transfer-0.2.2.dist-info/RECORD
