Metadata-Version: 2.1
Name: gp32-transfer
Version: 0.2.2
Summary: 
Author: Julien Muller
Author-email: muller.julien.02@gmail.com
Requires-Python: >=3.9,<4.0
Classifier: Programming Language :: Python :: 3
Classifier: Programming Language :: Python :: 3.10
Classifier: Programming Language :: Python :: 3.9
Requires-Dist: pandas (>=1.3.5,<2.0.0)
Requires-Dist: pyserial (==3.5)
Requires-Dist: typer (>=0.4.0,<0.5.0)
